LICENSE
README.md
setup.py
cbencryption/AES256CryptoProvider.py
cbencryption/JavaKeyStore.py
cbencryption/__init__.py
cbencryption.egg-info/PKG-INFO
cbencryption.egg-info/SOURCES.txt
cbencryption.egg-info/dependency_links.txt
cbencryption.egg-info/requires.txt
cbencryption.egg-info/top_level.txt
cbencryption.egg-info/zip-safe